{"mockup":{"controls":{"control":[{"ID":"92","h":"540","measuredH":"400","measuredW":"450","properties":{"color":"14540253","text":"A Web Page\nhttp://tchatme.com"},"typeID":"BrowserWindow","w":"960","x":"112","y":"40","zOrder":"0"},{"ID":"93","h":"70","measuredH":"70","measuredW":"100","typeID":"Canvas","w":"960","x":"112","y":"110","zOrder":"1"},{"ID":"94","measuredH":"28","measuredW":"88","properties":{"bold":"true","size":"20","text":"Tchat'me"},"typeID":"Label","x":"183","y":"131","zOrder":"2"},{"ID":"95","measuredH":"25","measuredW":"58","properties":{"bold":"false","size":"17","text":"Pierrick"},"typeID":"Label","x":"911","y":"131","zOrder":"3"},{"ID":"96","measuredH":"21","measuredW":"115","properties":{"text":"Mes salles de tchat"},"typeID":"Label","x":"331","y":"135","zOrder":"4"},{"ID":"97","measuredH":"21","measuredW":"146","properties":{"text":"Autres salles disponibles"},"typeID":"Label","x":"462","y":"135","zOrder":"5"},{"ID":"98","measuredH":"21","measuredW":"81","properties":{"text":"Les membres"},"typeID":"Label","x":"624","y":"135","zOrder":"6"},{"ID":"99","h":"49","measuredH":"70","measuredW":"100","typeID":"Canvas","w":"960","x":"112","y":"506","zOrder":"7"},{"ID":"100","measuredH":"21","measuredW":"113","properties":{"text":"Pierrick Antenen ©"},"typeID":"Label","x":"178","y":"520","zOrder":"8"},{"ID":"101","measuredH":"21","measuredW":"69","properties":{"text":"CFPT / TPI"},"typeID":"Label","x":"536","y":"520","zOrder":"9"},{"ID":"102","measuredH":"21","measuredW":"57","properties":{"text":"Juin 2017"},"typeID":"Label","x":"905","y":"520","zOrder":"10"},{"ID":"182","measuredH":"40","measuredW":"301","properties":{"size":"32","text":"Profil de pierrick1213"},"typeID":"Label","x":"183","y":"198","zOrder":"11"},{"ID":"183","h":"80","measuredH":"960","measuredW":"960","properties":{"src":{"Anchor":-1,"ID":"F4AC1737-EE6F-85AE-D62B-7C576DA090F1"}},"typeID":"Image","w":"80","x":"178","y":"238","zOrder":"12"},{"ID":"184","measuredH":"23","measuredW":"40","properties":{"bold":"true","size":"15","text":"Nom :"},"typeID":"Label","x":"178","y":"334","zOrder":"13"},{"ID":"185","measuredH":"23","measuredW":"64","properties":{"bold":"true","size":"15","text":"Prénom :"},"typeID":"Label","x":"178","y":"362","zOrder":"14"},{"ID":"186","measuredH":"23","measuredW":"61","properties":{"bold":"true","size":"15","text":"Pseudo :"},"typeID":"Label","x":"178","y":"392","zOrder":"15"},{"ID":"188","measuredH":"23","measuredW":"47","properties":{"bold":"true","size":"15","text":"Email :"},"typeID":"Label","x":"178","y":"422","zOrder":"16"},{"ID":"190","measuredH":"23","measuredW":"58","properties":{"bold":"false","size":"15","text":"Antenen"},"typeID":"Label","x":"267","y":"334","zOrder":"17"},{"ID":"191","measuredH":"23","measuredW":"52","properties":{"bold":"false","size":"15","text":"Pierrick"},"typeID":"Label","x":"267","y":"362","zOrder":"18"},{"ID":"192","measuredH":"23","measuredW":"81","properties":{"bold":"false","size":"15","text":"pierrick1213"},"typeID":"Label","x":"267","y":"392","zOrder":"19"},{"ID":"193","measuredH":"23","measuredW":"189","properties":{"bold":"false","size":"15","text":"pierrickantenen@gmail.com"},"typeID":"Label","x":"267","y":"422","zOrder":"20"},{"ID":"194","measuredH":"27","measuredW":"197","properties":{"color":"13576743","text":"Supprimer de ma liste d'amis"},"typeID":"Button","x":"772","y":"265","zOrder":"21"},{"ID":"195","h":"67","measuredH":"121","measuredW":"57","properties":{"color":"13576743","curvature":"-1","direction":"top","leftArrow":"true","p0":{"x":9,"y":0},"p1":{"x":0.54337899543379,"y":-0.3378995433789954},"p2":{"x":39,"y":66},"rightArrow":"false","text":""},"typeID":"Arrow","w":"40","x":"863","y":"359","zOrder":"22"},{"ID":"196","measuredH":"19","measuredW":"198","properties":{"size":"11","text":"si on connecté en tant que pierrick1213"},"typeID":"Label","x":"836","y":"426","zOrder":"23"},{"ID":"198","measuredH":"27","measuredW":"133","properties":{"color":"16777215","text":"Modifier mon profil"},"typeID":"Button","x":"836","y":"332","zOrder":"24"},{"ID":"199","h":"43","measuredH":"77","measuredW":"186","properties":{"color":"13576743","curvature":"-1","direction":"bottom","leftArrow":"true","p0":{"x":17,"y":0},"p1":{"x":0.4169508037018997,"y":0.2640038967364832},"p2":{"x":0,"y":42},"rightArrow":"false","text":""},"typeID":"Arrow","w":"23","x":"904","y":"292","zOrder":"25"},{"ID":"200","measuredH":"19","measuredW":"27","properties":{"size":"11","text":"sinon"},"typeID":"Label","x":"889","y":"304","zOrder":"26"}]},"measuredH":"580","measuredW":"1072","mockupH":"540","mockupW":"960","version":"1.0"}}